PyStoreDB/__init__.py
PyStoreDB/_delegates.py
PyStoreDB/_utils.py
PyStoreDB/conf.py
PyStoreDB/constants.py
PyStoreDB/errors.py
PyStoreDB/test.py
PyStoreDB/_impl/__init__.py
PyStoreDB/_impl/converter.py
PyStoreDB/_impl/query.py
PyStoreDB/core/__init__.py
PyStoreDB/core/aggregate.py
PyStoreDB/core/field_path.py
PyStoreDB/core/query.py
PyStoreDB/core/filters/__init__.py
PyStoreDB/core/filters/lookups.py
PyStoreDB/core/filters/utils.py
PyStoreDB/engines/__init__.py
PyStoreDB/engines/base.py
PyStoreDB/engines/_raw/__init__.py
PyStoreDB/engines/_raw/query.py
PyStoreDB/engines/_raw/utils.py
pystoredb-0.1.0.dist-info/LICENSE
pystoredb-0.1.0.dist-info/METADATA
pystoredb-0.1.0.dist-info/WHEEL
pystoredb-0.1.0.dist-info/top_level.txt
pystoredb-0.1.0.dist-info/RECORD
