Metadata-Version: 2.2
Name: PyStoreDB
Version: 0.1.0
Summary: A simple NoSQL database greatly inspired by Firestore and Django Filters.
Home-page: https://github.com/Wilfried-Tech/PyStoreDB
Author: Wilfried Tech
Author-email: wilfriedtech.dev@gmail.com
License: MIT
Classifier: Intended Audience :: Developers
Classifier: License :: OSI Approved :: MIT License
Classifier: Programming Language :: Python :: 3.9
Classifier: Operating System :: OS Independent
License-File: LICENSE
Dynamic: author
Dynamic: author-email
Dynamic: classifier
Dynamic: description
Dynamic: description-content-type
Dynamic: home-page
Dynamic: license
Dynamic: summary
